chara
tests
