Metadata-Version: 1.1
Name: chara
Version: 0.1.5
Summary: Chara enables developers to quickly create characterization tests.  Start by creating integration tests using whatever testing framework you prefer.  Using Chara you decorate those test functions to record interactions with specific dependencies.  Afterwards, you can replay the recording and those dependencies will behave as recorded.
Home-page: https://github.com/bywires/chara
Author: Bob McKee
Author-email: bmckee@bywires.com
License: MIT
Download-URL: https://github.com/bywires/chara/tarball/0.1.5
Keywords: record,replay,spy,test
Platform: UNKNOWN
Classifier: Development Status :: 4 - Beta
Classifier: Intended Audience :: Developers
Classifier: License :: OSI Approved :: MIT License
Classifier: Programming Language :: Python
Classifier: Programming Language :: Python :: 2.7
Classifier: Topic :: Software Development :: Libraries :: Python Modules
